hovercode/__init__.py
hovercode/base_client.py
hovercode/client.py
hovercode/enums.py
hovercode/exceptions.py
hovercode/hovercodes.py
hovercode/models.py
hovercode/py.typed
hovercode/types.py
hovercode/webhooks.py
hovercode-0.1.1.dist-info/licenses/LICENSE
hovercode-0.1.1.dist-info/METADATA
hovercode-0.1.1.dist-info/WHEEL
hovercode-0.1.1.dist-info/top_level.txt
hovercode-0.1.1.dist-info/RECORD
